ri_python_linter/.ruff.toml
ri_python_linter/__init__.py
ri_python_linter/setup.cfg
ri_python_linter-1.0.1.data/scripts/filter_files
ri_python_linter-1.0.1.data/scripts/format_files
ri_python_linter-1.0.1.data/scripts/get_ri_lint_config_path
ri_python_linter-1.0.1.data/scripts/get_ri_ruff_config_path
ri_python_linter-1.0.1.data/scripts/inc_cov
ri_python_linter-1.0.1.data/scripts/lint_files
ri_python_linter-1.0.1.data/scripts/list_files
ri_python_linter-1.0.1.data/scripts/run_ri_format
ri_python_linter-1.0.1.data/scripts/run_ri_lint
ri_python_linter-1.0.1.dist-info/METADATA
ri_python_linter-1.0.1.dist-info/WHEEL
ri_python_linter-1.0.1.dist-info/top_level.txt
ri_python_linter-1.0.1.dist-info/RECORD
